fh_prevail/__init__.py
fh_prevail/models.py
fh_prevail-0.1.6.dist-info/licenses/LICENSE
fh_prevail-0.1.6.dist-info/METADATA
fh_prevail-0.1.6.dist-info/WHEEL
fh_prevail-0.1.6.dist-info/top_level.txt
fh_prevail-0.1.6.dist-info/RECORD
