Metadata-Version: 2.4
Name: fh_prevail
Version: 0.1.6
Summary: A time-series forecasting model using UR2CUTE: Using Repetitively 2 CNN for Unsteady Timeseries Estimation
Home-page: https://github.com/FH-Prevail/UR2CUTE
Author: Sina Mirshahi
Author-email: sina7th@gmail.com
Classifier: Programming Language :: Python :: 3
Classifier: License :: OSI Approved :: MIT License
Classifier: Operating System :: OS Independent
Requires-Python: >=3.6
License-File: LICENSE
Requires-Dist: numpy
Requires-Dist: pandas
Requires-Dist: tensorflow
Requires-Dist: scikit-learn
Dynamic: author
Dynamic: author-email
Dynamic: classifier
Dynamic: description
Dynamic: description-content-type
Dynamic: home-page
Dynamic: license-file
Dynamic: requires-dist
Dynamic: requires-python
Dynamic: summary
